ivcap_ai_tool/__init__.py
ivcap_ai_tool/builder.py
ivcap_ai_tool/decorators.py
ivcap_ai_tool/executor.py
ivcap_ai_tool/logger.py
ivcap_ai_tool/logging.json
ivcap_ai_tool/mcp.py
ivcap_ai_tool/py.typed
ivcap_ai_tool/secret.py
ivcap_ai_tool/server.py
ivcap_ai_tool/service_definition.py
ivcap_ai_tool/utils.py
ivcap_ai_tool/version.py
ivcap_ai_tool-0.7.22.dist-info/AUTHORS.md
ivcap_ai_tool-0.7.22.dist-info/LICENSE
ivcap_ai_tool-0.7.22.dist-info/METADATA
ivcap_ai_tool-0.7.22.dist-info/WHEEL
ivcap_ai_tool-0.7.22.dist-info/RECORD
