Metadata-Version: 2.3
Name: ivcap_ai_tool
Version: 0.7.22
Summary: Helper functions for building AI Tools as IVCAP services
Author: Max Ott
Author-email: max.ott@csiro.au
Requires-Python: >=3.10,<4.0
Classifier: Programming Language :: Python :: 3
Classifier: Programming Language :: Python :: 3.10
Classifier: Programming Language :: Python :: 3.11
Classifier: Programming Language :: Python :: 3.12
Classifier: Programming Language :: Python :: 3.13
Requires-Dist: cachetools (>=5.5.2,<6.0.0)
Requires-Dist: fastapi (>=0.121.2,<0.122.0)
Requires-Dist: ivcap-service (>=0.6.16,<0.7.0)
Requires-Dist: opentelemetry-instrumentation-fastapi (>=0.51b0,<0.52)
Requires-Dist: uuid6 (==2024.7.10)
Requires-Dist: uvicorn (>=0.38.0,<0.39.0)
